imgui_bundle-1.92.3.dist-info/RECORD
imgui_bundle-1.92.3.dist-info/WHEEL
imgui_bundle-1.92.3.dist-info/entry_points.txt
imgui_bundle-1.92.3.dist-info/METADATA
imgui_bundle-1.92.3.dist-info/licenses/LICENSE
include/plutovg/plutovg.h
lib/libplutovg.a
lib/cmake/plutovg/plutovgConfig.cmake
lib/cmake/plutovg/plutovgTargets-release.cmake
lib/cmake/plutovg/plutovgTargets.cmake
lib/cmake/plutovg/plutovgConfigVersion.cmake
imgui_bundle/immvision.pyi
imgui_bundle/imgui_md.pyi
imgui_bundle/glfw_utils.py
imgui_bundle/imgui_color_text_edit.pyi
imgui_bundle/im_col32.py
imgui_bundle/_glfw_set_search_path.py
imgui_bundle/portable_file_dialogs.pyi
imgui_bundle/LICENSE
imgui_bundle/__init__.pyi
imgui_bundle/imgui_tex_inspect.pyi
imgui_bundle/notebook_patch_runners.py
imgui_bundle/imspinner.pyi
imgui_bundle/im_file_dialog.pyi
imgui_bundle/imgui_knobs.pyi
imgui_bundle/Readme_pypi.md
imgui_bundle/imgui_ctx.py
imgui_bundle/imgui_node_editor.pyi
imgui_bundle/__init__.py
imgui_bundle/imgui_bundle.pyi
imgui_bundle/libglfw.dylib
imgui_bundle/mypy.ini
imgui_bundle/.gitignore
imgui_bundle/hello_imgui.pyi
imgui_bundle/ruff.toml
imgui_bundle/imgui_node_editor_ctx.py
imgui_bundle/imguizmo.pyi
imgui_bundle/libglfw.3.dylib
imgui_bundle/py.typed
imgui_bundle/pyodide_patch_runners.py
imgui_bundle/imgui_pydantic.py
imgui_bundle/_imgui_bundle.cpython-311-darwin.so
imgui_bundle/imgui_command_palette.pyi
imgui_bundle/nanovg.pyi
imgui_bundle/imgui_fig.py
imgui_bundle/imgui_toggle.pyi
imgui_bundle/im_cool_bar.pyi
imgui_bundle/_patch_runners_add_save_screenshot_param.py
imgui_bundle/libglfw.3.3.dylib
imgui_bundle/python_backends/opengl_backend_programmable.py
imgui_bundle/python_backends/pyglet_backend.py
imgui_bundle/python_backends/__init__.py
imgui_bundle/python_backends/sdl3_backend.py
imgui_bundle/python_backends/Readme.md
imgui_bundle/python_backends/LICENSE_pyimgui.txt
imgui_bundle/python_backends/pygame_backend.py
imgui_bundle/python_backends/sdl2_backend.py
imgui_bundle/python_backends/opengl_base_backend.py
imgui_bundle/python_backends/glfw_backend.py
imgui_bundle/python_backends/examples_disabled/Readme.md
