Metadata-Version: 2.2
Name: imgui-bundle
Version: 1.92.3
Summary: Dear ImGui Bundle: From expressive code to powerful GUIs in no time. A fast, feature-rich, cross-platform toolkit for C++ and Python.
Author-Email: Pascal Thomet <pthomet@gmail.com>
Classifier: Development Status :: 5 - Production/Stable
Classifier: License :: OSI Approved :: MIT License
Classifier: Topic :: Scientific/Engineering
Classifier: Typing :: Typed
Classifier: Operating System :: OS Independent
Classifier: Programming Language :: Python :: 3 :: Only
Classifier: Programming Language :: Python :: 3.10
Classifier: Programming Language :: Python :: 3.11
Classifier: Programming Language :: Python :: 3.12
Project-URL: Homepage, https://pthom.github.io/imgui_bundle/
Project-URL: Documentation, https://pthom.github.io/imgui_bundle/
Project-URL: Repository, https://github.com/pthom/imgui_bundle
Project-URL: Issues, https://github.com/pthom/imgui_bundle/issues
Project-URL: Changelog, https://github.com/pthom/imgui_bundle/blob/main/CHANGELOG.md
Requires-Python: >=3.10
Requires-Dist: numpy
Requires-Dist: munch
Requires-Dist: glfw
Requires-Dist: PyOpenGL
Requires-Dist: pillow
Provides-Extra: test
Requires-Dist: pytest; extra == "test"
